MANIFEST.in
README.txt
setup.cfg
setup.py
Parlance.egg-info/PKG-INFO
Parlance.egg-info/SOURCES.txt
Parlance.egg-info/dependency_links.txt
Parlance.egg-info/entry_points.txt
Parlance.egg-info/requires.txt
Parlance.egg-info/top_level.txt
Parlance.egg-info/zip-safe
parlance/__init__.py
parlance/config.py
parlance/functions.py
parlance/gameboard.py
parlance/judge.py
parlance/language.py
parlance/main.py
parlance/network.py
parlance/orders.py
parlance/player.py
parlance/server.py
parlance/tokens.py
parlance/validation.py
parlance/xtended.py
parlance/data/protocol.html
parlance/data/standard.cfg
parlance/data/syntax.html