Metadata-Version: 1.0
Name: Parlance
Version: 1.4.1
Summary: A framework for playing the Diplomacy board game over a network.
Home-page: http://sourceforge.net/projects/parlance/
Author: Eric Wald
Author-email: breadman@users.sourceforge.net
License: Artistic License 2.0
Keywords: daide diplomacy board game server
Platform: Any
Classifier: Development Status :: 4 - Beta
Classifier: Environment :: Console
Classifier: Environment :: No Input/Output (Daemon)
Classifier: License :: OSI Approved :: Artistic License
Classifier: Natural Language :: English
Classifier: Operating System :: OS Independent
Classifier: Programming Language :: Python
Classifier: Topic :: Games/Entertainment :: Board Games
Classifier: Topic :: Games/Entertainment :: Turn Based Strategy
